pipeline/__init__.py
pipeline/fall_detect.py
pipeline/inference.py
pipeline/movenet_model.py
pipeline/pose_base.py
pipeline/pose_engine.py
pipeline/posenet_model.py
falldetect-1.0.9.dist-info/METADATA
falldetect-1.0.9.dist-info/WHEEL
falldetect-1.0.9.dist-info/top_level.txt
falldetect-1.0.9.dist-info/RECORD
