Metadata-Version: 2.1
Name: falldetect
Version: 1.0.9
Summary: Standalone Python ML library for people fall detection based on Tensorflow and PoseNet 2.0.
Home-page: https://ambianic.ai
Author: Bhavika Kanani, Ivelin Ivanov
Author-email: bhavika@softmaxai.com, ivelin.ivanov@ambianic.ai
License: Apache Software License 2.0
Platform: UNKNOWN
Classifier: Development Status :: 4 - Beta
Classifier: Programming Language :: Python :: 3
Classifier: License :: OSI Approved :: Apache Software License
Classifier: Operating System :: OS Independent
Classifier: Topic :: Software Development :: Embedded Systems
Classifier: Intended Audience :: Developers
Requires-Python: >=3.7
